LICENSE
MANIFEST.in
README.rst
setup.py
btc_sign_manager.egg-info/PKG-INFO
btc_sign_manager.egg-info/SOURCES.txt
btc_sign_manager.egg-info/dependency_links.txt
btc_sign_manager.egg-info/requires.txt
btc_sign_manager.egg-info/top_level.txt
sign_manager/__init__.py
sign_manager/admin.py
sign_manager/apps.py
sign_manager/collections.py
sign_manager/forms.py
sign_manager/helpers.py
sign_manager/models.py
sign_manager/service.py
sign_manager/signals.py
sign_manager/signet.py
sign_manager/tests.py
sign_manager/utils.py
sign_manager/views.py
sign_manager/migrations/0001_initial.py
sign_manager/migrations/0002_signature_length.py
sign_manager/migrations/0003_signature_length.py
sign_manager/migrations/0004_signmanagersignature_cert_key_algorithm_oid_and_more.py
sign_manager/migrations/0005_signmanagersignature_certificate.py
sign_manager/migrations/0006_remove_signmanagersignature_certificate_and_more.py
sign_manager/migrations/__init__.py
sign_manager/static/sign_manager/css/tray.css
sign_manager/static/sign_manager/img/close.svg
sign_manager/static/sign_manager/js/api.js
sign_manager/static/sign_manager/js/tray.js
sign_manager/templates/admin/sign_manager/signmanagersignature/change_form.html
sign_manager/templates/sign_manager/tray.html