Metadata-Version: 2.1
Name: btc-sign-manager
Version: 0.22
Summary: An application for cryptographic signing of models, files and etc.
Home-page: https://github.com/MEADez/btc-sign-manager
Author: MEADez
Author-email: m3adez@gmail.com
License: BSD License
Platform: UNKNOWN
Classifier: Environment :: Web Environment
Classifier: Framework :: Django
Classifier: Intended Audience :: Developers
Classifier: License :: OSI Approved :: BSD License
Classifier: Operating System :: OS Independent
Classifier: Programming Language :: Python :: 3.6
Classifier: Topic :: Internet :: WWW/HTTP
Classifier: Topic :: Internet :: WWW/HTTP :: Dynamic Content
License-File: LICENSE
